vampyhost.cp310-win_amd64.pyd
vamp/__init__.py
vamp/collect.py
vamp/frames.py
vamp/load.py
vamp/process.py
vamphost-1.3.2.dist-info/licenses/COPYING.rst
vamphost-1.3.2.dist-info/METADATA
vamphost-1.3.2.dist-info/WHEEL
vamphost-1.3.2.dist-info/top_level.txt
vamphost-1.3.2.dist-info/RECORD
