Metadata-Version: 2.4
Name: vamphost
Version: 1.3.2
Summary: Use Vamp plugins for audio feature analysis.
Home-page: https://code.soundsoftware.ac.uk/projects/vampy-host
Author: Chris Cannam, George Fazekas
Author-email: cannam@all-day-breakfast.com
License: MIT
Classifier: Development Status :: 4 - Beta
Classifier: Intended Audience :: Science/Research
Classifier: Intended Audience :: Developers
Classifier: License :: OSI Approved :: MIT License
Classifier: Operating System :: MacOS :: MacOS X
Classifier: Operating System :: Microsoft :: Windows
Classifier: Operating System :: POSIX
Classifier: Programming Language :: Python
Classifier: Programming Language :: Python :: 3
Classifier: Topic :: Multimedia :: Sound/Audio :: Analysis
Requires-Python: >=3.10
License-File: COPYING.rst
Requires-Dist: numpy
Dynamic: author
Dynamic: author-email
Dynamic: classifier
Dynamic: description
Dynamic: home-page
Dynamic: license
Dynamic: license-file
Dynamic: requires-dist
Dynamic: requires-python
Dynamic: summary
